dbCon.py
dfManuplate.py
smenan.py
smenan-0.0.4.dist-info/METADATA
smenan-0.0.4.dist-info/WHEEL
smenan-0.0.4.dist-info/top_level.txt
smenan-0.0.4.dist-info/RECORD
