Metadata-Version: 2.1
Name: smenan
Version: 0.0.4
Summary: Developed for Sade Tech. Corp.
Home-page: https://github.com/Flowmot1on/smart-energy-planner
Author: Yunus Emre Emik
Author-email: yunus_emre3497@hotmail.com
License: UNKNOWN
Platform: UNKNOWN
Classifier: Programming Language :: Python :: 3
Classifier: Programming Language :: Python :: 3
Classifier: Programming Language :: Python :: 3
Classifier: License :: OSI Approved :: GNU General Public License v2 or later (GPLv2+)
Classifier: Operating System :: OS Independent
Requires-Dist: absl-py (~=0.9.0)
Requires-Dist: altgraph (~=0.17)
Requires-Dist: astunparse (~=1.6.3)
Requires-Dist: auto-py-to-exe (~=2.7.8)
Requires-Dist: bottle (~=0.12.18)
Requires-Dist: bottle-websocket (~=0.2.9)
Requires-Dist: cachetools (~=4.1.1)
Requires-Dist: certifi (~=2020.6.20)
Requires-Dist: cffi (~=1.14.2)
Requires-Dist: chardet (~=3.0.4)
Requires-Dist: configparser (~=5.0.0)
Requires-Dist: Eel (~=0.12.4)
Requires-Dist: flatbuffers (~=1.12)
Requires-Dist: future (~=0.18.2)
Requires-Dist: gast (~=0.3.3)
Requires-Dist: gevent (~=20.6.2)
Requires-Dist: gevent-websocket (~=0.10.1)
Requires-Dist: google-auth (~=1.20.1)
Requires-Dist: google-auth-oauthlib (~=0.4.1)
Requires-Dist: google-pasta (~=0.2.0)
Requires-Dist: greenlet (~=0.4.16)
Requires-Dist: grpcio (~=1.31.0)
Requires-Dist: h5py (~=2.10.0)
Requires-Dist: idna (~=2.10)
Requires-Dist: joblib (~=0.16.0)
Requires-Dist: Keras (~=2.4.3)
Requires-Dist: Keras-Preprocessing (~=1.1.2)
Requires-Dist: Markdown (~=3.2.2)
Requires-Dist: numpy (~=1.18.5)
Requires-Dist: oauthlib (~=3.1.0)
Requires-Dist: opt-einsum (~=3.3.0)
Requires-Dist: pandas (~=1.1.0)
Requires-Dist: pefile (~=2019.4.18)
Requires-Dist: protobuf (~=3.13.0)
Requires-Dist: py2exe (~=0.9.2.2)
Requires-Dist: pyasn1 (~=0.4.8)
Requires-Dist: pyasn1-modules (~=0.2.8)
Requires-Dist: pycparser (~=2.20)
Requires-Dist: pyinstaller (~=4.0)
Requires-Dist: pyinstaller-hooks-contrib (~=2020.7)
Requires-Dist: pyodbc (~=4.0.30)
Requires-Dist: python-dateutil (~=2.8.1)
Requires-Dist: pytz (~=2020.1)
Requires-Dist: pywin32-ctypes (~=0.2.0)
Requires-Dist: PyYAML (~=5.3.1)
Requires-Dist: requests (~=2.24.0)
Requires-Dist: requests-oauthlib (~=1.3.0)
Requires-Dist: rsa (~=4.6)
Requires-Dist: scikit-learn (~=0.23.2)
Requires-Dist: scipy (~=1.4.1)
Requires-Dist: six (~=1.15.0)
Requires-Dist: sklearn (~=0.0)
Requires-Dist: tensorboard (~=2.3.0)
Requires-Dist: tensorboard-plugin-wit (~=1.7.0)
Requires-Dist: tensorflow (~=2.3.0)
Requires-Dist: tensorflow-estimator (~=2.3.0)
Requires-Dist: termcolor (~=1.1.0)
Requires-Dist: tflite (~=2.3.0)
Requires-Dist: threadpoolctl (~=2.1.0)
Requires-Dist: urllib3 (~=1.25.10)
Requires-Dist: Werkzeug (~=1.0.1)
Requires-Dist: whichcraft (~=0.6.1)
Requires-Dist: wrapt (~=1.12.1)
Requires-Dist: zope.event (~=4.4)
Requires-Dist: zope.interface (~=5.1.0)
